odoo/addons/stock_picking_origin_reference/README.rst
odoo/addons/stock_picking_origin_reference/__init__.py
odoo/addons/stock_picking_origin_reference/__manifest__.py
odoo/addons/stock_picking_origin_reference/i18n/stock_picking_origin_reference.pot
odoo/addons/stock_picking_origin_reference/models/__init__.py
odoo/addons/stock_picking_origin_reference/models/stock_picking.py
odoo/addons/stock_picking_origin_reference/readme/CONFIGURE.rst
odoo/addons/stock_picking_origin_reference/readme/CONTRIBUTORS.rst
odoo/addons/stock_picking_origin_reference/readme/DESCRIPTION.rst
odoo/addons/stock_picking_origin_reference/static/description/icon.png
odoo/addons/stock_picking_origin_reference/static/description/index.html
odoo/addons/stock_picking_origin_reference/tests/__init__.py
odoo/addons/stock_picking_origin_reference/tests/test_stock_picking_origin_reference.py
odoo/addons/stock_picking_origin_reference/views/stock_picking_views.xml
odoo13_addon_stock_picking_origin_reference-13.0.1.0.1.dev4.dist-info/METADATA
odoo13_addon_stock_picking_origin_reference-13.0.1.0.1.dev4.dist-info/WHEEL
odoo13_addon_stock_picking_origin_reference-13.0.1.0.1.dev4.dist-info/top_level.txt
odoo13_addon_stock_picking_origin_reference-13.0.1.0.1.dev4.dist-info/RECORD
